[
  {
    "name": "General",
    "settings": [
      {
        "type": "url",
        "id": "default_shop_page",
        "label": "Default Shop Page",
        "info": "Where the landing page + header logos link to.  Default: 'collections/all'"
      }
    ]
  },
  {
    "name": "Homepage",
    "settings": [
      {
        "type": "image_picker",
        "id": "index_bg_image",
        "label": "Homepage Background Image"
      },
      {
        "type": "radio",
        "id": "index_logo_color",
        "label": "Homepage Logo Color",
        "options": [
          { "value": "white", "label": "White" },
          { "value": "black", "label": "Black" }
        ],
        "default": "white"
      }
    ]
  },
  {
    "name": "Social media",
    "settings": [
      {
        "type": "header",
        "content": "Accounts"
      },
      {
        "type": "text",
        "id": "social_instagram_link",
        "label": "Instagram",
        "info": "https:\/\/instagram.com\/shopify"
      },
      {
        "type": "text",
        "id": "social_facebook_link",
        "label": "Facebook",
        "info": "https:\/\/www.facebook.com\/shopify"
      }
    ]
  }
]